{
  "evaluated": {
    "1v_5cOmtsn_D2MuAyO8zRMwpnLxRRoNSy": {
      "filename": "PXL_20260312_152020439.mp4",
      "evaluated_at": "2026-03-12T22:52:16.729774",
      "report_json_id": null,
      "report_md_id": null,
      "overall_score": 4.5,
      "recommendation": "No"
    },
    "1-OQ3hTvodhTJ90ZFtNEPYw-XFwuwfE-E": {
      "filename": "WhatsApp Video 2026-03-13 at 17.15.21.mp4",
      "evaluated_at": "2026-03-13T23:50:23.853516",
      "report_json_id": null,
      "report_md_id": null,
      "overall_score": 7.05,
      "recommendation": "Yes"
    },
    "18VQsOkdcGBGldZTQKXfPDETfsSjwbBOz": {
      "filename": "WhatsApp Video 2026-03-13 at 4.53.37 PM.mp4",
      "evaluated_at": "2026-03-13T23:50:39.152274",
      "report_json_id": null,
      "report_md_id": null,
      "overall_score": 5.7,
      "recommendation": "Maybe"
    }
  }
}